odoo/addons/mail_gateway/README.rst
odoo/addons/mail_gateway/__init__.py
odoo/addons/mail_gateway/__manifest__.py
odoo/addons/mail_gateway/hooks.py
odoo/addons/mail_gateway/controllers/__init__.py
odoo/addons/mail_gateway/controllers/gateway.py
odoo/addons/mail_gateway/i18n/es.po
odoo/addons/mail_gateway/i18n/it.po
odoo/addons/mail_gateway/i18n/mail_gateway.pot
odoo/addons/mail_gateway/models/__init__.py
odoo/addons/mail_gateway/models/discuss_channel.py
odoo/addons/mail_gateway/models/ir_websocket.py
odoo/addons/mail_gateway/models/mail_gateway.py
odoo/addons/mail_gateway/models/mail_gateway_abstract.py
odoo/addons/mail_gateway/models/mail_guest.py
odoo/addons/mail_gateway/models/mail_message.py
odoo/addons/mail_gateway/models/mail_notification.py
odoo/addons/mail_gateway/models/mail_thread.py
odoo/addons/mail_gateway/models/res_partner.py
odoo/addons/mail_gateway/models/res_users.py
odoo/addons/mail_gateway/models/res_users_settings.py
odoo/addons/mail_gateway/readme/CONFIGURATION.rst
odoo/addons/mail_gateway/readme/CONTRIBUTORS.md
odoo/addons/mail_gateway/readme/CREDITS.md
odoo/addons/mail_gateway/readme/DESCRIPTION.md
odoo/addons/mail_gateway/readme/ROADMAP.md
odoo/addons/mail_gateway/readme/USAGE.md
odoo/addons/mail_gateway/security/ir.model.access.csv
odoo/addons/mail_gateway/security/security.xml
odoo/addons/mail_gateway/static/description/icon.png
odoo/addons/mail_gateway/static/description/index.html
odoo/addons/mail_gateway/static/src/components/chatter/chatter.esm.js
odoo/addons/mail_gateway/static/src/components/chatter/chatter.xml
odoo/addons/mail_gateway/static/src/components/composer/composer.esm.js
odoo/addons/mail_gateway/static/src/components/gateway_follower/gateway_follower.esm.js
odoo/addons/mail_gateway/static/src/components/gateway_follower/gateway_follower.scss
odoo/addons/mail_gateway/static/src/components/gateway_follower/gateway_follower.xml
odoo/addons/mail_gateway/static/src/components/message/message.xml
odoo_addon_mail_gateway-18.0.1.0.6.dist-info/METADATA
odoo_addon_mail_gateway-18.0.1.0.6.dist-info/WHEEL
odoo_addon_mail_gateway-18.0.1.0.6.dist-info/top_level.txt
odoo_addon_mail_gateway-18.0.1.0.6.dist-info/RECORD
